easy_block_builder/__init__.py
easy_block_builder/block.py
easy_block_builder/ctx.py
easy_block_builder/registry.py
eblock-0.3.0.dist-info/licenses/LICENSE
eblock-0.3.0.dist-info/METADATA
eblock-0.3.0.dist-info/WHEEL
eblock-0.3.0.dist-info/top_level.txt
eblock-0.3.0.dist-info/RECORD
