Metadata-Version: 2.4
Name: eblock
Version: 0.3.0
Summary: A flexible, schema-driven library for building dynamic, context-aware content blocks with variable substitution, nested composition, validation, and asynchronous rendering.
Author: GAKiknadze
License: Apache-2.0
Project-URL: Homepage, https://github.com/GAKiknadze/easy_block_builder
Project-URL: Repository, https://github.com/GAKiknadze/easy_block_builder
Project-URL: Documentation, https://github.com/GAKiknadze/easy_block_builder#readme
Project-URL: Issues, https://github.com/GAKiknadze/easy_block_builder/issues
Keywords: block,builder,dynamic,page,ui,template,pydantic,variable substitution,async,context
Classifier: Development Status :: 3 - Alpha
Classifier: Intended Audience :: Developers
Classifier: Programming Language :: Python :: 3
Classifier: Programming Language :: Python :: 3.10
Classifier: Programming Language :: Python :: 3.11
Classifier: Programming Language :: Python :: 3.12
Classifier: Programming Language :: Python :: 3.13
Classifier: Framework :: AsyncIO
Classifier: Topic :: Software Development :: Libraries :: Python Modules
Classifier: Topic :: Internet :: WWW/HTTP
Classifier: Topic :: Text Processing :: Markup
Requires-Python: >=3.10
License-File: LICENSE
Requires-Dist: pydantic>=2.12.4
Dynamic: license-file
